bcf_vcf.py
helper_functions.py
hmm_functions.py
main.py
myHmm-0.0.2.dist-info/LICENSE.txt
myHmm-0.0.2.dist-info/METADATA
myHmm-0.0.2.dist-info/WHEEL
myHmm-0.0.2.dist-info/entry_points.txt
myHmm-0.0.2.dist-info/top_level.txt
myHmm-0.0.2.dist-info/RECORD
