Metadata-Version: 2.1
Name: myHmm
Version: 0.0.2
Summary: Find introgressed segments
Home-page: https://github.com/LauritsSkov/Introgression-detection
Author: Laurits Skov and Moises Coll Macia
Author-email: lauritsskov2@gmail.com
License: UNKNOWN
Platform: UNKNOWN
Classifier: Programming Language :: Python :: 3
Classifier: Programming Language :: Python :: 3.6
Classifier: Programming Language :: Python :: 3.7
Classifier: License :: OSI Approved :: MIT License
Requires-Dist: numpy (>=1.15)
Requires-Dist: scipy (>=1.5)
Requires-Dist: numba
